setup.py
ajax_changelist/__init__.py
ajax_changelist/admin.py
django_ajax_changelist.egg-info/PKG-INFO
django_ajax_changelist.egg-info/SOURCES.txt
django_ajax_changelist.egg-info/dependency_links.txt
django_ajax_changelist.egg-info/requires.txt
django_ajax_changelist.egg-info/top_level.txt
django_ajax_changelist.egg-info/zip-safe