Metadata-Version: 1.0
Name: django-ajax-changelist
Version: 0.1.3
Summary: Django ModelAdmin extended to support editing selected fields via AJAX without leaving the changelist.
Home-page: UNKNOWN
Author: Ben Regenspan
Author-email: ben@sohotechlabs.com
License: MIT
Platform: UNKNOWN
